py_sandboxed-0.1.1.dist-info/licenses/LICENSE
py_sandboxer/__init__.py
py_sandboxer/exceptions.py
py_sandboxer/rules.py
py_sandboxer/sandbox.py
py_sandboxed-0.1.1.dist-info/METADATA
py_sandboxed-0.1.1.dist-info/WHEEL
py_sandboxed-0.1.1.dist-info/top_level.txt
py_sandboxed-0.1.1.dist-info/RECORD
