Metadata-Version: 2.4
Name: py-sandboxed
Version: 0.1.1
Summary: Configurable Execution Sandboxing for Python.
Author-email: Ira Abbott <ira@mycloud.blue>
License: BSD-1-Clause
Requires-Python: >=3.8
License-File: LICENSE
Dynamic: license-file
